setup.py
audt_distributions/Binomialdistribution.py
audt_distributions/Gaussiandistribution.py
audt_distributions/Generaldistribution.py
audt_distributions/__init__.py
audt_distributions.egg-info/PKG-INFO
audt_distributions.egg-info/SOURCES.txt
audt_distributions.egg-info/dependency_links.txt
audt_distributions.egg-info/not-zip-safe
audt_distributions.egg-info/top_level.txt