Metadata-Version: 1.0
Name: audt-distributions
Version: 1.0
Summary: Gaussian and Binomial distributions
Home-page: UNKNOWN
Author: AudST
Author-email: contactme@gmail.com
License: UNKNOWN
Platform: UNKNOWN
